curv_logger/__init__.py
curv_logger-0.0.0.2.dist-info/LICENSE
curv_logger-0.0.0.2.dist-info/METADATA
curv_logger-0.0.0.2.dist-info/WHEEL
curv_logger-0.0.0.2.dist-info/top_level.txt
curv_logger-0.0.0.2.dist-info/RECORD
