Metadata-Version: 2.1
Name: curv-logger
Version: 0.0.0.2
Summary: UNKNOWN
Home-page: http://github.com/rep-ai/curv-logger
License: MIT
Platform: UNKNOWN
Requires-Dist: dataclasses
Requires-Dist: dataclasses-json
